bing/BasicAPI.py
bing/Bing.py
bing/__init__.py
bing/normalize_company_name.py
bing/rename_dict_keys.py
bing-0.31.dist-info/LICENSE
bing-0.31.dist-info/METADATA
bing-0.31.dist-info/WHEEL
bing-0.31.dist-info/top_level.txt
bing-0.31.dist-info/RECORD
